bonfire/Bot.py
bonfire/__init__.py
bonfire/method/__init__.py
bonfire/method/button.py
bonfire/method/delete.py
bonfire/method/edit.py
bonfire/method/message.py
bonfire/method/reply.py
bonfire/method/send.py
bonfire/method/sticker.py
bonfire_tg_libraly-1.0.9.dist-info/LICENSE
bonfire_tg_libraly-1.0.9.dist-info/METADATA
bonfire_tg_libraly-1.0.9.dist-info/WHEEL
bonfire_tg_libraly-1.0.9.dist-info/top_level.txt
bonfire_tg_libraly-1.0.9.dist-info/RECORD
