Metadata-Version: 2.1
Name: bonfire-tg-libraly
Version: 1.0.9
Summary: Speed telegram api libraly
Home-page: https://github.com/Help-urself/bonfire
Author: Alex_Stepens
Author-email: ianacist01@gmail.com
License: UNKNOWN
Platform: UNKNOWN
Classifier: Programming Language :: Python :: 3.7
Classifier: Programming Language :: Python :: 3.8
Classifier: Programming Language :: Python :: 3.9
Classifier: Programming Language :: Python :: 3.10
Classifier: License :: OSI Approved :: MIT License
Classifier: Operating System :: OS Independent
Requires-Python: >=3.8
